pyaxo_ng.py
pyaxo_ng-1.0.1.dist-info/COPYING
pyaxo_ng-1.0.1.dist-info/METADATA
pyaxo_ng-1.0.1.dist-info/WHEEL
pyaxo_ng-1.0.1.dist-info/top_level.txt
pyaxo_ng-1.0.1.dist-info/RECORD
