Metadata-Version: 2.1
Name: pyaxo-ng
Version: 1.0.1
Summary: Python implementation of the Axolotl ratchet protocol
Home-page: https://github.com/i404788/pyaxo-ng
Author: Ferris Kwaijtaal
License: GPLv3
Platform: UNKNOWN
Classifier: License :: OSI Approved :: GNU General Public License v3 (GPLv3)
Classifier: Programming Language :: Python :: 3
Classifier: Programming Language :: Python :: 3.7
Requires-Dist: pycryptodome (>=3.9.8)
Requires-Dist: pynacl (>=1.4.0)
Requires-Dist: diskcache (>=4.1.0)
